{
 "entity": "LAKELAND",
 "source": "ted_rlgf_city_workbook",
 "fiscal_years": [
  2016,
  2017,
  2018,
  2019,
  2020,
  2021,
  2022,
  2023
 ],
 "totals": [
  {
   "fiscal_year": 2016,
   "revenue": 2568966,
   "expenditure": 2201386,
   "expenditure_operating": 1854152,
   "expenditure_capital": 347234
  },
  {
   "fiscal_year": 2017,
   "revenue": 3083031,
   "expenditure": 2279542,
   "expenditure_operating": 1854937,
   "expenditure_capital": 424605
  },
  {
   "fiscal_year": 2018,
   "revenue": 2836414,
   "expenditure": 2362109,
   "expenditure_operating": 2110022,
   "expenditure_capital": 252087
  },
  {
   "fiscal_year": 2019,
   "revenue": 2772978,
   "expenditure": 2244428,
   "expenditure_operating": 2145027,
   "expenditure_capital": 99401
  },
  {
   "fiscal_year": 2020,
   "revenue": 2945534,
   "expenditure": 2418016,
   "expenditure_operating": 2084288,
   "expenditure_capital": 333728
  },
  {
   "fiscal_year": 2021,
   "revenue": 4004111,
   "expenditure": 2985915,
   "expenditure_operating": 2302053,
   "expenditure_capital": 683862
  },
  {
   "fiscal_year": 2022,
   "revenue": 2907981,
   "expenditure": 2649001,
   "expenditure_operating": 2395477,
   "expenditure_capital": 253524
  },
  {
   "fiscal_year": 2023,
   "revenue": 3324364,
   "expenditure": 2746299,
   "expenditure_operating": 2595237,
   "expenditure_capital": 151062
  }
 ],
 "breakdown": [
  {
   "classification": "TOTAL REVENUES",
   "category": "revenue",
   "section": "revenues",
   "depth": 0,
   "path": "TOTAL REVENUES",
   "amounts": {
    "2016": 2568966,
    "2017": 3083031,
    "2018": 2836414,
    "2019": 2772978,
    "2020": 2945534,
    "2021": 4004111,
    "2022": 2907981,
    "2023": 3324364
   }
  },
  {
   "classification": "GENERAL REVENUES",
   "category": "revenue",
   "section": "revenues",
   "depth": 1,
   "path": "TOTAL REVENUES > GENERAL REVENUES",
   "amounts": {
    "2016": 2263500,
    "2017": 2120041,
    "2018": 1874903,
    "2019": 1853743,
    "2020": 2019500,
    "2021": 3090805,
    "2022": 1980267,
    "2023": 2332949
   }
  },
  {
   "classification": "PART I TAX REVENUES",
   "category": "revenue",
   "section": "revenues",
   "depth": 2,
   "path": "TOTAL REVENUES > GENERAL REVENUES > PART I TAX REVENUES",
   "amounts": {
    "2016": 1273048,
    "2017": 1278201,
    "2018": 1339551,
    "2019": 1357507,
    "2020": 1299894,
    "2021": 1391396,
    "2022": 1427023,
    "2023": 1584581
   }
  },
  {
   "classification": "PART 2 INTERGOVERNMENTAL REVENUES",
   "category": "revenue",
   "section": "revenues",
   "depth": 2,
   "path": "TOTAL REVENUES > GENERAL REVENUES > PART 2 INTERGOVERNMENTAL REVENUES",
   "amounts": {
    "2016": 862354,
    "2017": 701394,
    "2018": 378807,
    "2019": 357209,
    "2020": 546769,
    "2021": 1534695,
    "2022": 342879,
    "2023": 475060
   }
  },
  {
   "classification": "PART 3 SERVICE CHARGES AND OTHER REVENUES",
   "category": "revenue",
   "section": "revenues",
   "depth": 2,
   "path": "TOTAL REVENUES > GENERAL REVENUES > PART 3 SERVICE CHARGES AND OTHER REVENUES",
   "amounts": {
    "2016": 128098,
    "2017": 140446,
    "2018": 156545,
    "2019": 139027,
    "2020": 172837,
    "2021": 164714,
    "2022": 210365,
    "2023": 273308
   }
  },
  {
   "classification": "ENTERPRISE FUND REVENUES",
   "category": "revenue",
   "section": "revenues",
   "depth": 1,
   "path": "TOTAL REVENUES > ENTERPRISE FUND REVENUES",
   "amounts": {
    "2016": 305466,
    "2017": 962990,
    "2018": 961511,
    "2019": 919235,
    "2020": 926034,
    "2021": 913306,
    "2022": 927714,
    "2023": 991415
   }
  },
  {
   "classification": "Part 4 REVENUES FROM PUBLIC UTILITY SYSTEMS AND OTHER ENTERPRISE FUNDS",
   "category": "revenue",
   "section": "revenues",
   "depth": 2,
   "path": "TOTAL REVENUES > ENTERPRISE FUND REVENUES > Part 4 REVENUES FROM PUBLIC UTILITY SYSTEMS AND OTHER ENTERPRISE FUNDS",
   "amounts": {
    "2016": 305466,
    "2017": 962990,
    "2018": 961511,
    "2019": 919235,
    "2020": 926034,
    "2021": 913306,
    "2022": 927714,
    "2023": 991415
   }
  },
  {
   "classification": "TOTAL CURRENT OPERATING EXPENDITURES",
   "category": "expenditure",
   "section": "operating",
   "depth": 0,
   "path": "TOTAL CURRENT OPERATING EXPENDITURES",
   "amounts": {
    "2016": 1854152,
    "2017": 1854937,
    "2018": 2110022,
    "2019": 2145027,
    "2020": 2084288,
    "2021": 2302053,
    "2022": 2395477,
    "2023": 2595237
   }
  },
  {
   "classification": "PART V GENERAL GOVERNMENT EXPENDITURES",
   "category": "expenditure",
   "section": "operating",
   "depth": 1,
   "path": "TOTAL CURRENT OPERATING EXPENDITURES > PART V GENERAL GOVERNMENT EXPENDITURES",
   "amounts": {
    "2016": 1197980,
    "2017": 1182712,
    "2018": 1341987,
    "2019": 1411465,
    "2020": 1460998,
    "2021": 1602279,
    "2022": 1509726,
    "2023": 1595796
   }
  },
  {
   "classification": "Section A General Government",
   "category": "expenditure",
   "section": "operating",
   "depth": 2,
   "path": "TOTAL CURRENT OPERATING EXPENDITURES > PART V GENERAL GOVERNMENT EXPENDITURES > Section A General Government",
   "amounts": {
    "2016": 329209,
    "2017": 364985,
    "2018": 262682,
    "2019": 356839,
    "2020": 251459,
    "2021": 332242,
    "2022": 326502,
    "2023": 306608
   }
  },
  {
   "classification": "Section B Judicial",
   "category": "expenditure",
   "section": "operating",
   "depth": 2,
   "path": "TOTAL CURRENT OPERATING EXPENDITURES > PART V GENERAL GOVERNMENT EXPENDITURES > Section B Judicial",
   "amounts": {
    "2016": 0,
    "2017": 5992,
    "2018": 1283,
    "2019": 4648,
    "2020": 4169,
    "2021": 4844,
    "2022": 4685,
    "2023": 3548
   }
  },
  {
   "classification": "Section C Public Safety",
   "category": "expenditure",
   "section": "operating",
   "depth": 2,
   "path": "TOTAL CURRENT OPERATING EXPENDITURES > PART V GENERAL GOVERNMENT EXPENDITURES > Section C Public Safety",
   "amounts": {
    "2016": 526208,
    "2017": 519870,
    "2018": 628565,
    "2019": 618989,
    "2020": 640679,
    "2021": 706231,
    "2022": 715371,
    "2023": 646108
   }
  },
  {
   "classification": "Section D Public Works",
   "category": "expenditure",
   "section": "operating",
   "depth": 2,
   "path": "TOTAL CURRENT OPERATING EXPENDITURES > PART V GENERAL GOVERNMENT EXPENDITURES > Section D Public Works",
   "amounts": {
    "2016": 314079,
    "2017": 253621,
    "2018": 439457,
    "2019": 420809,
    "2020": 526892,
    "2021": 520712,
    "2022": 434094,
    "2023": 612210
   }
  },
  {
   "classification": "Section E Health and Welfare",
   "category": "expenditure",
   "section": "operating",
   "depth": 2,
   "path": "TOTAL CURRENT OPERATING EXPENDITURES > PART V GENERAL GOVERNMENT EXPENDITURES > Section E Health and Welfare",
   "amounts": {
    "2016": 22884,
    "2017": 24344,
    "2018": 0,
    "2019": 0,
    "2020": 0,
    "2021": 0,
    "2022": 0,
    "2023": 0
   }
  },
  {
   "classification": "Section G Housing and Development",
   "category": "expenditure",
   "section": "operating",
   "depth": 2,
   "path": "TOTAL CURRENT OPERATING EXPENDITURES > PART V GENERAL GOVERNMENT EXPENDITURES > Section G Housing and Development",
   "amounts": {
    "2016": 0,
    "2017": 5300,
    "2018": 5000,
    "2019": 5180,
    "2020": 32799,
    "2021": 33250,
    "2022": 24074,
    "2023": 22322
   }
  },
  {
   "classification": "PART VI EXPENSES FOR PUBLIC UTILITY SYSTEMS AND OTHER ENTERPRISE FUNDS",
   "category": "expenditure",
   "section": "operating",
   "depth": 1,
   "path": "TOTAL CURRENT OPERATING EXPENDITURES > PART VI EXPENSES FOR PUBLIC UTILITY SYSTEMS AND OTHER ENTERPRISE FUNDS",
   "amounts": {
    "2016": 656172,
    "2017": 672225,
    "2018": 768035,
    "2019": 733562,
    "2020": 623290,
    "2021": 699774,
    "2022": 885751,
    "2023": 999441
   }
  },
  {
   "classification": "Enterprise Fund Current Operations Expense",
   "category": "expenditure",
   "section": "operating",
   "depth": 2,
   "path": "TOTAL CURRENT OPERATING EXPENDITURES > PART VI EXPENSES FOR PUBLIC UTILITY SYSTEMS AND OTHER ENTERPRISE FUNDS > Enterprise Fund Current Operations Expense",
   "amounts": {
    "2016": 656172,
    "2017": 672225,
    "2018": 768035,
    "2019": 733562,
    "2020": 623290,
    "2021": 699774,
    "2022": 885751,
    "2023": 999441
   }
  },
  {
   "classification": "Enterprise Fund Interest Expense",
   "category": "expenditure",
   "section": "operating",
   "depth": 2,
   "path": "TOTAL CURRENT OPERATING EXPENDITURES > PART VI EXPENSES FOR PUBLIC UTILITY SYSTEMS AND OTHER ENTERPRISE FUNDS > Enterprise Fund Interest Expense",
   "amounts": {
    "2016": 32926,
    "2017": 27337,
    "2018": 22563,
    "2019": 16399,
    "2020": 9023,
    "2021": 2365,
    "2022": 156,
    "2023": 125
   }
  },
  {
   "classification": "PART X INTERGOVERNMENTAL EXPENDITURES",
   "category": "expenditure",
   "section": "operating",
   "depth": 1,
   "path": "TOTAL CURRENT OPERATING EXPENDITURES > PART X INTERGOVERNMENTAL EXPENDITURES",
   "amounts": {
    "2016": 0,
    "2017": 0,
    "2018": 0,
    "2019": 0,
    "2020": 0,
    "2021": 0,
    "2022": 0,
    "2023": 0
   }
  },
  {
   "classification": "PART V CAPITAL EXPENDITURES",
   "category": "expenditure",
   "section": "capital",
   "depth": 0,
   "path": "PART V CAPITAL EXPENDITURES",
   "amounts": {
    "2016": 347234,
    "2017": 424605,
    "2018": 252087,
    "2019": 99401,
    "2020": 333728,
    "2021": 683862,
    "2022": 253524,
    "2023": 151062
   }
  },
  {
   "classification": "Capital Expenditures - Property",
   "category": "expenditure",
   "section": "capital",
   "depth": 1,
   "path": "PART V CAPITAL EXPENDITURES > Capital Expenditures - Property",
   "amounts": {
    "2016": 291395,
    "2017": 387288,
    "2018": 103471,
    "2019": 60312,
    "2020": 198007,
    "2021": 576638,
    "2022": 114802,
    "2023": 81374
   }
  },
  {
   "classification": "Section A General Government - Property",
   "category": "expenditure",
   "section": "capital",
   "depth": 2,
   "path": "PART V CAPITAL EXPENDITURES > Capital Expenditures - Property > Section A General Government - Property",
   "amounts": {
    "2016": 0,
    "2017": 78498,
    "2018": 0,
    "2019": 0,
    "2020": 0,
    "2021": 0,
    "2022": 0,
    "2023": 0
   }
  },
  {
   "classification": "Section B Judicial - Property",
   "category": "expenditure",
   "section": "capital",
   "depth": 2,
   "path": "PART V CAPITAL EXPENDITURES > Capital Expenditures - Property > Section B Judicial - Property",
   "amounts": {
    "2016": 0,
    "2017": 0,
    "2018": 0,
    "2019": 0,
    "2020": 0,
    "2021": 0,
    "2022": 0,
    "2023": 0
   }
  },
  {
   "classification": "Section C Public Safety - Property",
   "category": "expenditure",
   "section": "capital",
   "depth": 2,
   "path": "PART V CAPITAL EXPENDITURES > Capital Expenditures - Property > Section C Public Safety - Property",
   "amounts": {
    "2016": 0,
    "2017": 0,
    "2018": 0,
    "2019": 0,
    "2020": 0,
    "2021": 0,
    "2022": 0,
    "2023": 0
   }
  },
  {
   "classification": "Section D Public Works - Property",
   "category": "expenditure",
   "section": "capital",
   "depth": 2,
   "path": "PART V CAPITAL EXPENDITURES > Capital Expenditures - Property > Section D Public Works - Property",
   "amounts": {
    "2016": 291395,
    "2017": 308790,
    "2018": 103471,
    "2019": 60312,
    "2020": 198007,
    "2021": 576638,
    "2022": 114802,
    "2023": 81374
   }
  },
  {
   "classification": "Section E Health and Welfare - Property",
   "category": "expenditure",
   "section": "capital",
   "depth": 2,
   "path": "PART V CAPITAL EXPENDITURES > Capital Expenditures - Property > Section E Health and Welfare - Property",
   "amounts": {
    "2016": 0,
    "2017": 0,
    "2018": 0,
    "2019": 0,
    "2020": 0,
    "2021": 0,
    "2022": 0,
    "2023": 0
   }
  },
  {
   "classification": "Section F Culture and Recreation - Property",
   "category": "expenditure",
   "section": "capital",
   "depth": 2,
   "path": "PART V CAPITAL EXPENDITURES > Capital Expenditures - Property > Section F Culture and Recreation - Property",
   "amounts": {
    "2016": 0,
    "2017": 0,
    "2018": 0,
    "2019": 0,
    "2020": 0,
    "2021": 0,
    "2022": 0,
    "2023": 0
   }
  },
  {
   "classification": "Section G Housing and Development - Property",
   "category": "expenditure",
   "section": "capital",
   "depth": 2,
   "path": "PART V CAPITAL EXPENDITURES > Capital Expenditures - Property > Section G Housing and Development - Property",
   "amounts": {
    "2016": 0,
    "2017": 0,
    "2018": 0,
    "2019": 0,
    "2020": 0,
    "2021": 0,
    "2022": 0,
    "2023": 0
   }
  },
  {
   "classification": "Capital Expenditures - Machinery and Equipment",
   "category": "expenditure",
   "section": "capital",
   "depth": 1,
   "path": "PART V CAPITAL EXPENDITURES > Capital Expenditures - Machinery and Equipment",
   "amounts": {
    "2016": 55839,
    "2017": 37317,
    "2018": 148616,
    "2019": 39089,
    "2020": 135721,
    "2021": 107224,
    "2022": 138722,
    "2023": 69688
   }
  },
  {
   "classification": "Section A General Government Machinery and Equipment",
   "category": "expenditure",
   "section": "capital",
   "depth": 2,
   "path": "PART V CAPITAL EXPENDITURES > Capital Expenditures - Machinery and Equipment > Section A General Government Machinery and Equipment",
   "amounts": {
    "2016": 0,
    "2017": 0,
    "2018": 17600,
    "2019": 0,
    "2020": 0,
    "2021": 0,
    "2022": 0,
    "2023": 0
   }
  },
  {
   "classification": "Section B Judicial - Machinery and Equipment",
   "category": "expenditure",
   "section": "capital",
   "depth": 2,
   "path": "PART V CAPITAL EXPENDITURES > Capital Expenditures - Machinery and Equipment > Section B Judicial - Machinery and Equipment",
   "amounts": {
    "2016": 0,
    "2017": 0,
    "2018": 0,
    "2019": 0,
    "2020": 0,
    "2021": 0,
    "2022": 0,
    "2023": 0
   }
  },
  {
   "classification": "Section C Public Safety - Machinery and Equipment",
   "category": "expenditure",
   "section": "capital",
   "depth": 2,
   "path": "PART V CAPITAL EXPENDITURES > Capital Expenditures - Machinery and Equipment > Section C Public Safety - Machinery and Equipment",
   "amounts": {
    "2016": 46737,
    "2017": 37317,
    "2018": 30684,
    "2019": 19544,
    "2020": 60820,
    "2021": 35217,
    "2022": 45007,
    "2023": 39364
   }
  },
  {
   "classification": "Section D Public Works - Machinery and Equipment",
   "category": "expenditure",
   "section": "capital",
   "depth": 2,
   "path": "PART V CAPITAL EXPENDITURES > Capital Expenditures - Machinery and Equipment > Section D Public Works - Machinery and Equipment",
   "amounts": {
    "2016": 9102,
    "2017": 0,
    "2018": 100332,
    "2019": 19545,
    "2020": 74901,
    "2021": 72007,
    "2022": 93715,
    "2023": 30324
   }
  },
  {
   "classification": "Section E Health and Welfare - Machinery and Equipment",
   "category": "expenditure",
   "section": "capital",
   "depth": 2,
   "path": "PART V CAPITAL EXPENDITURES > Capital Expenditures - Machinery and Equipment > Section E Health and Welfare - Machinery and Equipment",
   "amounts": {
    "2016": 0,
    "2017": 0,
    "2018": 0,
    "2019": 0,
    "2020": 0,
    "2021": 0,
    "2022": 0,
    "2023": 0
   }
  },
  {
   "classification": "Section F Culture and Recreation - Machinery and Equipment",
   "category": "expenditure",
   "section": "capital",
   "depth": 2,
   "path": "PART V CAPITAL EXPENDITURES > Capital Expenditures - Machinery and Equipment > Section F Culture and Recreation - Machinery and Equipment",
   "amounts": {
    "2016": 0,
    "2017": 0,
    "2018": 0,
    "2019": 0,
    "2020": 0,
    "2021": 0,
    "2022": 0,
    "2023": 0
   }
  },
  {
   "classification": "Section G Housing and Development - Machinery and Equipment",
   "category": "expenditure",
   "section": "capital",
   "depth": 2,
   "path": "PART V CAPITAL EXPENDITURES > Capital Expenditures - Machinery and Equipment > Section G Housing and Development - Machinery and Equipment",
   "amounts": {
    "2016": 0,
    "2017": 0,
    "2018": 0,
    "2019": 0,
    "2020": 0,
    "2021": 0,
    "2022": 0,
    "2023": 0
   }
  },
  {
   "classification": "Capital Expenditures - Intangibles",
   "category": "expenditure",
   "section": "capital",
   "depth": 1,
   "path": "PART V CAPITAL EXPENDITURES > Capital Expenditures - Intangibles",
   "amounts": {
    "2016": 0,
    "2017": 0,
    "2018": 0,
    "2019": 0,
    "2020": 0,
    "2021": 0,
    "2022": 0,
    "2023": 0
   }
  },
  {
   "classification": "Section A General Government - Intangibles",
   "category": "expenditure",
   "section": "capital",
   "depth": 2,
   "path": "PART V CAPITAL EXPENDITURES > Capital Expenditures - Intangibles > Section A General Government - Intangibles",
   "amounts": {
    "2016": 0,
    "2017": 0,
    "2018": 0,
    "2019": 0,
    "2020": 0,
    "2021": 0,
    "2022": 0,
    "2023": 0
   }
  },
  {
   "classification": "Section B Judicial - Intangibles",
   "category": "expenditure",
   "section": "capital",
   "depth": 2,
   "path": "PART V CAPITAL EXPENDITURES > Capital Expenditures - Intangibles > Section B Judicial - Intangibles",
   "amounts": {
    "2016": 0,
    "2017": 0,
    "2018": 0,
    "2019": 0,
    "2020": 0,
    "2021": 0,
    "2022": 0,
    "2023": 0
   }
  },
  {
   "classification": "Section C Public Safety - Intangibles",
   "category": "expenditure",
   "section": "capital",
   "depth": 2,
   "path": "PART V CAPITAL EXPENDITURES > Capital Expenditures - Intangibles > Section C Public Safety - Intangibles",
   "amounts": {
    "2016": 0,
    "2017": 0,
    "2018": 0,
    "2019": 0,
    "2020": 0,
    "2021": 0,
    "2022": 0,
    "2023": 0
   }
  },
  {
   "classification": "Section D Public Works - Intangibles",
   "category": "expenditure",
   "section": "capital",
   "depth": 2,
   "path": "PART V CAPITAL EXPENDITURES > Capital Expenditures - Intangibles > Section D Public Works - Intangibles",
   "amounts": {
    "2016": 0,
    "2017": 0,
    "2018": 0,
    "2019": 0,
    "2020": 0,
    "2021": 0,
    "2022": 0,
    "2023": 0
   }
  },
  {
   "classification": "Section E Health and Welfare _ Intangibles",
   "category": "expenditure",
   "section": "capital",
   "depth": 2,
   "path": "PART V CAPITAL EXPENDITURES > Capital Expenditures - Intangibles > Section E Health and Welfare _ Intangibles",
   "amounts": {
    "2016": 0,
    "2017": 0,
    "2018": 0,
    "2019": 0,
    "2020": 0,
    "2021": 0,
    "2022": 0,
    "2023": 0
   }
  },
  {
   "classification": "Section F Culture and Recreation - Intangibles",
   "category": "expenditure",
   "section": "capital",
   "depth": 2,
   "path": "PART V CAPITAL EXPENDITURES > Capital Expenditures - Intangibles > Section F Culture and Recreation - Intangibles",
   "amounts": {
    "2016": 0,
    "2017": 0,
    "2018": 0,
    "2019": 0,
    "2020": 0,
    "2021": 0,
    "2022": 0,
    "2023": 0
   }
  },
  {
   "classification": "Section G Housing and Development - Intangibles",
   "category": "expenditure",
   "section": "capital",
   "depth": 2,
   "path": "PART V CAPITAL EXPENDITURES > Capital Expenditures - Intangibles > Section G Housing and Development - Intangibles",
   "amounts": {
    "2016": 0,
    "2017": 0,
    "2018": 0,
    "2019": 0,
    "2020": 0,
    "2021": 0,
    "2022": 0,
    "2023": 0
   }
  }
 ]
}
