{
 "entity": "WRIGHTSVILLE",
 "source": "ted_rlgf_city_workbook",
 "fiscal_years": [
  2016,
  2017,
  2018,
  2019,
  2020,
  2021,
  2022,
  2023
 ],
 "totals": [
  {
   "fiscal_year": 2016,
   "revenue": 2352791,
   "expenditure": 1996444,
   "expenditure_operating": 1911335,
   "expenditure_capital": 85109
  },
  {
   "fiscal_year": 2017,
   "revenue": 2607955,
   "expenditure": 2029700,
   "expenditure_operating": 1884139,
   "expenditure_capital": 145561
  },
  {
   "fiscal_year": 2018,
   "revenue": 3084190,
   "expenditure": 2229980,
   "expenditure_operating": 2179280,
   "expenditure_capital": 50700
  },
  {
   "fiscal_year": 2019,
   "revenue": 3239290,
   "expenditure": 2158883,
   "expenditure_operating": 2111872,
   "expenditure_capital": 47011
  },
  {
   "fiscal_year": 2020,
   "revenue": 3648732,
   "expenditure": 2899187,
   "expenditure_operating": 2588217,
   "expenditure_capital": 310970
  },
  {
   "fiscal_year": 2021,
   "revenue": 4594094,
   "expenditure": 2718085,
   "expenditure_operating": 2231898,
   "expenditure_capital": 486187
  },
  {
   "fiscal_year": 2022,
   "revenue": 4855236,
   "expenditure": 1908298,
   "expenditure_operating": 1713323,
   "expenditure_capital": 194975
  },
  {
   "fiscal_year": 2023,
   "revenue": 3879467,
   "expenditure": 2477800,
   "expenditure_operating": 2383165,
   "expenditure_capital": 94635
  }
 ],
 "breakdown": [
  {
   "classification": "TOTAL REVENUES",
   "category": "revenue",
   "section": "revenues",
   "depth": 0,
   "path": "TOTAL REVENUES",
   "amounts": {
    "2016": 2352791,
    "2017": 2607955,
    "2018": 3084190,
    "2019": 3239290,
    "2020": 3648732,
    "2021": 4594094,
    "2022": 4855236,
    "2023": 3879467
   }
  },
  {
   "classification": "GENERAL REVENUES",
   "category": "revenue",
   "section": "revenues",
   "depth": 1,
   "path": "TOTAL REVENUES > GENERAL REVENUES",
   "amounts": {
    "2016": 1448826,
    "2017": 1638714,
    "2018": 2098717,
    "2019": 2047736,
    "2020": 2547843,
    "2021": 2562529,
    "2022": 2816862,
    "2023": 1879571
   }
  },
  {
   "classification": "PART I TAX REVENUES",
   "category": "revenue",
   "section": "revenues",
   "depth": 2,
   "path": "TOTAL REVENUES > GENERAL REVENUES > PART I TAX REVENUES",
   "amounts": {
    "2016": 955596,
    "2017": 1073191,
    "2018": 1128517,
    "2019": 1121610,
    "2020": 1163969,
    "2021": 1241251,
    "2022": 1177895,
    "2023": 1283480
   }
  },
  {
   "classification": "PART 2 INTERGOVERNMENTAL REVENUES",
   "category": "revenue",
   "section": "revenues",
   "depth": 2,
   "path": "TOTAL REVENUES > GENERAL REVENUES > PART 2 INTERGOVERNMENTAL REVENUES",
   "amounts": {
    "2016": 173406,
    "2017": 251537,
    "2018": 624426,
    "2019": 498822,
    "2020": 1123543,
    "2021": 1039650,
    "2022": 1349297,
    "2023": 288294
   }
  },
  {
   "classification": "PART 3 SERVICE CHARGES AND OTHER REVENUES",
   "category": "revenue",
   "section": "revenues",
   "depth": 2,
   "path": "TOTAL REVENUES > GENERAL REVENUES > PART 3 SERVICE CHARGES AND OTHER REVENUES",
   "amounts": {
    "2016": 319824,
    "2017": 313986,
    "2018": 345774,
    "2019": 427304,
    "2020": 260331,
    "2021": 281628,
    "2022": 289670,
    "2023": 307797
   }
  },
  {
   "classification": "ENTERPRISE FUND REVENUES",
   "category": "revenue",
   "section": "revenues",
   "depth": 1,
   "path": "TOTAL REVENUES > ENTERPRISE FUND REVENUES",
   "amounts": {
    "2016": 903965,
    "2017": 969241,
    "2018": 985473,
    "2019": 1191554,
    "2020": 1100889,
    "2021": 2031565,
    "2022": 2038374,
    "2023": 1999896
   }
  },
  {
   "classification": "Part 4 REVENUES FROM PUBLIC UTILITY SYSTEMS AND OTHER ENTERPRISE FUNDS",
   "category": "revenue",
   "section": "revenues",
   "depth": 2,
   "path": "TOTAL REVENUES > ENTERPRISE FUND REVENUES > Part 4 REVENUES FROM PUBLIC UTILITY SYSTEMS AND OTHER ENTERPRISE FUNDS",
   "amounts": {
    "2016": 903965,
    "2017": 969241,
    "2018": 985473,
    "2019": 1191554,
    "2020": 1100889,
    "2021": 2031565,
    "2022": 2038374,
    "2023": 1999896
   }
  },
  {
   "classification": "TOTAL CURRENT OPERATING EXPENDITURES",
   "category": "expenditure",
   "section": "operating",
   "depth": 0,
   "path": "TOTAL CURRENT OPERATING EXPENDITURES",
   "amounts": {
    "2016": 1911335,
    "2017": 1884139,
    "2018": 2179280,
    "2019": 2111872,
    "2020": 2588217,
    "2021": 2231898,
    "2022": 1713323,
    "2023": 2383165
   }
  },
  {
   "classification": "PART V GENERAL GOVERNMENT EXPENDITURES",
   "category": "expenditure",
   "section": "operating",
   "depth": 1,
   "path": "TOTAL CURRENT OPERATING EXPENDITURES > PART V GENERAL GOVERNMENT EXPENDITURES",
   "amounts": {
    "2016": 1110606,
    "2017": 1149515,
    "2018": 1400809,
    "2019": 1237959,
    "2020": 1759572,
    "2021": 1324441,
    "2022": 1713323,
    "2023": 1587798
   }
  },
  {
   "classification": "Section A General Government",
   "category": "expenditure",
   "section": "operating",
   "depth": 2,
   "path": "TOTAL CURRENT OPERATING EXPENDITURES > PART V GENERAL GOVERNMENT EXPENDITURES > Section A General Government",
   "amounts": {
    "2016": 275745,
    "2017": 263333,
    "2018": 295399,
    "2019": 285890,
    "2020": 305404,
    "2021": 277459,
    "2022": 290588,
    "2023": 303745
   }
  },
  {
   "classification": "Section B Judicial",
   "category": "expenditure",
   "section": "operating",
   "depth": 2,
   "path": "TOTAL CURRENT OPERATING EXPENDITURES > PART V GENERAL GOVERNMENT EXPENDITURES > Section B Judicial",
   "amounts": {
    "2016": 0,
    "2017": 0,
    "2018": 0,
    "2019": 0,
    "2020": 0,
    "2021": 0,
    "2022": 0,
    "2023": 0
   }
  },
  {
   "classification": "Section C Public Safety",
   "category": "expenditure",
   "section": "operating",
   "depth": 2,
   "path": "TOTAL CURRENT OPERATING EXPENDITURES > PART V GENERAL GOVERNMENT EXPENDITURES > Section C Public Safety",
   "amounts": {
    "2016": 577850,
    "2017": 613631,
    "2018": 591344,
    "2019": 646621,
    "2020": 626463,
    "2021": 643699,
    "2022": 690329,
    "2023": 764093
   }
  },
  {
   "classification": "Section D Public Works",
   "category": "expenditure",
   "section": "operating",
   "depth": 2,
   "path": "TOTAL CURRENT OPERATING EXPENDITURES > PART V GENERAL GOVERNMENT EXPENDITURES > Section D Public Works",
   "amounts": {
    "2016": 230011,
    "2017": 245551,
    "2018": 487066,
    "2019": 273948,
    "2020": 797705,
    "2021": 371783,
    "2022": 675406,
    "2023": 474960
   }
  },
  {
   "classification": "Section E Health and Welfare",
   "category": "expenditure",
   "section": "operating",
   "depth": 2,
   "path": "TOTAL CURRENT OPERATING EXPENDITURES > PART V GENERAL GOVERNMENT EXPENDITURES > Section E Health and Welfare",
   "amounts": {
    "2016": 0,
    "2017": 0,
    "2018": 0,
    "2019": 0,
    "2020": 0,
    "2021": 0,
    "2022": 0,
    "2023": 0
   }
  },
  {
   "classification": "Section G Housing and Development",
   "category": "expenditure",
   "section": "operating",
   "depth": 2,
   "path": "TOTAL CURRENT OPERATING EXPENDITURES > PART V GENERAL GOVERNMENT EXPENDITURES > Section G Housing and Development",
   "amounts": {
    "2016": 0,
    "2017": 0,
    "2018": 0,
    "2019": 4500,
    "2020": 3000,
    "2021": 4500,
    "2022": 12000,
    "2023": 18000
   }
  },
  {
   "classification": "PART VI EXPENSES FOR PUBLIC UTILITY SYSTEMS AND OTHER ENTERPRISE FUNDS",
   "category": "expenditure",
   "section": "operating",
   "depth": 1,
   "path": "TOTAL CURRENT OPERATING EXPENDITURES > PART VI EXPENSES FOR PUBLIC UTILITY SYSTEMS AND OTHER ENTERPRISE FUNDS",
   "amounts": {
    "2016": 773729,
    "2017": 734624,
    "2018": 778471,
    "2019": 873913,
    "2020": 828645,
    "2021": 907457,
    "2022": 0,
    "2023": 795367
   }
  },
  {
   "classification": "Enterprise Fund Current Operations Expense",
   "category": "expenditure",
   "section": "operating",
   "depth": 2,
   "path": "TOTAL CURRENT OPERATING EXPENDITURES > PART VI EXPENSES FOR PUBLIC UTILITY SYSTEMS AND OTHER ENTERPRISE FUNDS > Enterprise Fund Current Operations Expense",
   "amounts": {
    "2016": 773729,
    "2017": 734624,
    "2018": 778471,
    "2019": 873913,
    "2020": 828645,
    "2021": 907457,
    "2022": 0,
    "2023": 795367
   }
  },
  {
   "classification": "Enterprise Fund Interest Expense",
   "category": "expenditure",
   "section": "operating",
   "depth": 2,
   "path": "TOTAL CURRENT OPERATING EXPENDITURES > PART VI EXPENSES FOR PUBLIC UTILITY SYSTEMS AND OTHER ENTERPRISE FUNDS > Enterprise Fund Interest Expense",
   "amounts": {
    "2016": 0,
    "2017": 0,
    "2018": 0,
    "2019": 0,
    "2020": 0,
    "2021": 2438,
    "2022": 0,
    "2023": 43053
   }
  },
  {
   "classification": "PART X INTERGOVERNMENTAL EXPENDITURES",
   "category": "expenditure",
   "section": "operating",
   "depth": 1,
   "path": "TOTAL CURRENT OPERATING EXPENDITURES > PART X INTERGOVERNMENTAL EXPENDITURES",
   "amounts": {
    "2016": 27000,
    "2017": 27000,
    "2018": 27000,
    "2019": 30000,
    "2020": 30000,
    "2021": 31500,
    "2022": 57000,
    "2023": 39000
   }
  },
  {
   "classification": "PART V CAPITAL EXPENDITURES",
   "category": "expenditure",
   "section": "capital",
   "depth": 0,
   "path": "PART V CAPITAL EXPENDITURES",
   "amounts": {
    "2016": 85109,
    "2017": 145561,
    "2018": 50700,
    "2019": 47011,
    "2020": 310970,
    "2021": 486187,
    "2022": 194975,
    "2023": 94635
   }
  },
  {
   "classification": "Capital Expenditures - Property",
   "category": "expenditure",
   "section": "capital",
   "depth": 1,
   "path": "PART V CAPITAL EXPENDITURES > Capital Expenditures - Property",
   "amounts": {
    "2016": 0,
    "2017": 120000,
    "2018": 0,
    "2019": 0,
    "2020": 0,
    "2021": 352392,
    "2022": 50977,
    "2023": 84941
   }
  },
  {
   "classification": "Section A General Government - Property",
   "category": "expenditure",
   "section": "capital",
   "depth": 2,
   "path": "PART V CAPITAL EXPENDITURES > Capital Expenditures - Property > Section A General Government - Property",
   "amounts": {
    "2016": 0,
    "2017": 0,
    "2018": 0,
    "2019": 0,
    "2020": 0,
    "2021": 320384,
    "2022": 40154,
    "2023": 84941
   }
  },
  {
   "classification": "Section B Judicial - Property",
   "category": "expenditure",
   "section": "capital",
   "depth": 2,
   "path": "PART V CAPITAL EXPENDITURES > Capital Expenditures - Property > Section B Judicial - Property",
   "amounts": {
    "2016": 0,
    "2017": 0,
    "2018": 0,
    "2019": 0,
    "2020": 0,
    "2021": 0,
    "2022": 0,
    "2023": 0
   }
  },
  {
   "classification": "Section C Public Safety - Property",
   "category": "expenditure",
   "section": "capital",
   "depth": 2,
   "path": "PART V CAPITAL EXPENDITURES > Capital Expenditures - Property > Section C Public Safety - Property",
   "amounts": {
    "2016": 0,
    "2017": 120000,
    "2018": 0,
    "2019": 0,
    "2020": 0,
    "2021": 0,
    "2022": 10823,
    "2023": 0
   }
  },
  {
   "classification": "Section D Public Works - Property",
   "category": "expenditure",
   "section": "capital",
   "depth": 2,
   "path": "PART V CAPITAL EXPENDITURES > Capital Expenditures - Property > Section D Public Works - Property",
   "amounts": {
    "2016": 0,
    "2017": 0,
    "2018": 0,
    "2019": 0,
    "2020": 0,
    "2021": 32008,
    "2022": 0,
    "2023": 0
   }
  },
  {
   "classification": "Section E Health and Welfare - Property",
   "category": "expenditure",
   "section": "capital",
   "depth": 2,
   "path": "PART V CAPITAL EXPENDITURES > Capital Expenditures - Property > Section E Health and Welfare - Property",
   "amounts": {
    "2016": 0,
    "2017": 0,
    "2018": 0,
    "2019": 0,
    "2020": 0,
    "2021": 0,
    "2022": 0,
    "2023": 0
   }
  },
  {
   "classification": "Section F Culture and Recreation - Property",
   "category": "expenditure",
   "section": "capital",
   "depth": 2,
   "path": "PART V CAPITAL EXPENDITURES > Capital Expenditures - Property > Section F Culture and Recreation - Property",
   "amounts": {
    "2016": 0,
    "2017": 0,
    "2018": 0,
    "2019": 0,
    "2020": 0,
    "2021": 0,
    "2022": 0,
    "2023": 0
   }
  },
  {
   "classification": "Section G Housing and Development - Property",
   "category": "expenditure",
   "section": "capital",
   "depth": 2,
   "path": "PART V CAPITAL EXPENDITURES > Capital Expenditures - Property > Section G Housing and Development - Property",
   "amounts": {
    "2016": 0,
    "2017": 0,
    "2018": 0,
    "2019": 0,
    "2020": 0,
    "2021": 0,
    "2022": 0,
    "2023": 0
   }
  },
  {
   "classification": "Capital Expenditures - Machinery and Equipment",
   "category": "expenditure",
   "section": "capital",
   "depth": 1,
   "path": "PART V CAPITAL EXPENDITURES > Capital Expenditures - Machinery and Equipment",
   "amounts": {
    "2016": 85109,
    "2017": 25561,
    "2018": 50700,
    "2019": 47011,
    "2020": 310970,
    "2021": 133795,
    "2022": 143998,
    "2023": 9694
   }
  },
  {
   "classification": "Section A General Government Machinery and Equipment",
   "category": "expenditure",
   "section": "capital",
   "depth": 2,
   "path": "PART V CAPITAL EXPENDITURES > Capital Expenditures - Machinery and Equipment > Section A General Government Machinery and Equipment",
   "amounts": {
    "2016": 414,
    "2017": 0,
    "2018": 0,
    "2019": 0,
    "2020": 2160,
    "2021": 4983,
    "2022": 0,
    "2023": 8286
   }
  },
  {
   "classification": "Section B Judicial - Machinery and Equipment",
   "category": "expenditure",
   "section": "capital",
   "depth": 2,
   "path": "PART V CAPITAL EXPENDITURES > Capital Expenditures - Machinery and Equipment > Section B Judicial - Machinery and Equipment",
   "amounts": {
    "2016": 0,
    "2017": 0,
    "2018": 0,
    "2019": 0,
    "2020": 0,
    "2021": 0,
    "2022": 0,
    "2023": 0
   }
  },
  {
   "classification": "Section C Public Safety - Machinery and Equipment",
   "category": "expenditure",
   "section": "capital",
   "depth": 2,
   "path": "PART V CAPITAL EXPENDITURES > Capital Expenditures - Machinery and Equipment > Section C Public Safety - Machinery and Equipment",
   "amounts": {
    "2016": 84695,
    "2017": 25561,
    "2018": 44863,
    "2019": 47011,
    "2020": 308810,
    "2021": 101625,
    "2022": 36950,
    "2023": 1408
   }
  },
  {
   "classification": "Section D Public Works - Machinery and Equipment",
   "category": "expenditure",
   "section": "capital",
   "depth": 2,
   "path": "PART V CAPITAL EXPENDITURES > Capital Expenditures - Machinery and Equipment > Section D Public Works - Machinery and Equipment",
   "amounts": {
    "2016": 0,
    "2017": 0,
    "2018": 5837,
    "2019": 0,
    "2020": 0,
    "2021": 27187,
    "2022": 107048,
    "2023": 0
   }
  },
  {
   "classification": "Section E Health and Welfare - Machinery and Equipment",
   "category": "expenditure",
   "section": "capital",
   "depth": 2,
   "path": "PART V CAPITAL EXPENDITURES > Capital Expenditures - Machinery and Equipment > Section E Health and Welfare - Machinery and Equipment",
   "amounts": {
    "2016": 0,
    "2017": 0,
    "2018": 0,
    "2019": 0,
    "2020": 0,
    "2021": 0,
    "2022": 0,
    "2023": 0
   }
  },
  {
   "classification": "Section F Culture and Recreation - Machinery and Equipment",
   "category": "expenditure",
   "section": "capital",
   "depth": 2,
   "path": "PART V CAPITAL EXPENDITURES > Capital Expenditures - Machinery and Equipment > Section F Culture and Recreation - Machinery and Equipment",
   "amounts": {
    "2016": 0,
    "2017": 0,
    "2018": 0,
    "2019": 0,
    "2020": 0,
    "2021": 0,
    "2022": 0,
    "2023": 0
   }
  },
  {
   "classification": "Section G Housing and Development - Machinery and Equipment",
   "category": "expenditure",
   "section": "capital",
   "depth": 2,
   "path": "PART V CAPITAL EXPENDITURES > Capital Expenditures - Machinery and Equipment > Section G Housing and Development - Machinery and Equipment",
   "amounts": {
    "2016": 0,
    "2017": 0,
    "2018": 0,
    "2019": 0,
    "2020": 0,
    "2021": 0,
    "2022": 0,
    "2023": 0
   }
  },
  {
   "classification": "Capital Expenditures - Intangibles",
   "category": "expenditure",
   "section": "capital",
   "depth": 1,
   "path": "PART V CAPITAL EXPENDITURES > Capital Expenditures - Intangibles",
   "amounts": {
    "2016": 0,
    "2017": 0,
    "2018": 0,
    "2019": 0,
    "2020": 0,
    "2021": 0,
    "2022": 0,
    "2023": 0
   }
  },
  {
   "classification": "Section A General Government - Intangibles",
   "category": "expenditure",
   "section": "capital",
   "depth": 2,
   "path": "PART V CAPITAL EXPENDITURES > Capital Expenditures - Intangibles > Section A General Government - Intangibles",
   "amounts": {
    "2016": 0,
    "2017": 0,
    "2018": 0,
    "2019": 0,
    "2020": 0,
    "2021": 0,
    "2022": 0,
    "2023": 0
   }
  },
  {
   "classification": "Section B Judicial - Intangibles",
   "category": "expenditure",
   "section": "capital",
   "depth": 2,
   "path": "PART V CAPITAL EXPENDITURES > Capital Expenditures - Intangibles > Section B Judicial - Intangibles",
   "amounts": {
    "2016": 0,
    "2017": 0,
    "2018": 0,
    "2019": 0,
    "2020": 0,
    "2021": 0,
    "2022": 0,
    "2023": 0
   }
  },
  {
   "classification": "Section C Public Safety - Intangibles",
   "category": "expenditure",
   "section": "capital",
   "depth": 2,
   "path": "PART V CAPITAL EXPENDITURES > Capital Expenditures - Intangibles > Section C Public Safety - Intangibles",
   "amounts": {
    "2016": 0,
    "2017": 0,
    "2018": 0,
    "2019": 0,
    "2020": 0,
    "2021": 0,
    "2022": 0,
    "2023": 0
   }
  },
  {
   "classification": "Section D Public Works - Intangibles",
   "category": "expenditure",
   "section": "capital",
   "depth": 2,
   "path": "PART V CAPITAL EXPENDITURES > Capital Expenditures - Intangibles > Section D Public Works - Intangibles",
   "amounts": {
    "2016": 0,
    "2017": 0,
    "2018": 0,
    "2019": 0,
    "2020": 0,
    "2021": 0,
    "2022": 0,
    "2023": 0
   }
  },
  {
   "classification": "Section E Health and Welfare _ Intangibles",
   "category": "expenditure",
   "section": "capital",
   "depth": 2,
   "path": "PART V CAPITAL EXPENDITURES > Capital Expenditures - Intangibles > Section E Health and Welfare _ Intangibles",
   "amounts": {
    "2016": 0,
    "2017": 0,
    "2018": 0,
    "2019": 0,
    "2020": 0,
    "2021": 0,
    "2022": 0,
    "2023": 0
   }
  },
  {
   "classification": "Section F Culture and Recreation - Intangibles",
   "category": "expenditure",
   "section": "capital",
   "depth": 2,
   "path": "PART V CAPITAL EXPENDITURES > Capital Expenditures - Intangibles > Section F Culture and Recreation - Intangibles",
   "amounts": {
    "2016": 0,
    "2017": 0,
    "2018": 0,
    "2019": 0,
    "2020": 0,
    "2021": 0,
    "2022": 0,
    "2023": 0
   }
  },
  {
   "classification": "Section G Housing and Development - Intangibles",
   "category": "expenditure",
   "section": "capital",
   "depth": 2,
   "path": "PART V CAPITAL EXPENDITURES > Capital Expenditures - Intangibles > Section G Housing and Development - Intangibles",
   "amounts": {
    "2016": 0,
    "2017": 0,
    "2018": 0,
    "2019": 0,
    "2020": 0,
    "2021": 0,
    "2022": 0,
    "2023": 0
   }
  },
  {
   "classification": "Revenue Bond Debt Beginning Amount Outstanding",
   "category": "debt",
   "section": "debt",
   "depth": 2,
   "path": "PART XI DEBT OUTSTANDING, ISSUED, RETIRED DURING FISCAL YEAR > Section A Revenue Bond Debt > Revenue Bond Debt Beginning Amount Outstanding",
   "amounts": {
    "2016": 0,
    "2017": 0,
    "2018": 0,
    "2019": 0,
    "2020": 0,
    "2021": 0,
    "2022": 0,
    "2023": 4480290
   }
  },
  {
   "classification": "Revenue Bond Debt New Issued Amount",
   "category": "debt",
   "section": "debt",
   "depth": 2,
   "path": "PART XI DEBT OUTSTANDING, ISSUED, RETIRED DURING FISCAL YEAR > Section A Revenue Bond Debt > Revenue Bond Debt New Issued Amount",
   "amounts": {
    "2016": 0,
    "2017": 0,
    "2018": 0,
    "2019": 0,
    "2020": 0,
    "2021": 0,
    "2022": 0,
    "2023": 0
   }
  },
  {
   "classification": "Revenue Bond Debt Amount Retired",
   "category": "debt",
   "section": "debt",
   "depth": 2,
   "path": "PART XI DEBT OUTSTANDING, ISSUED, RETIRED DURING FISCAL YEAR > Section A Revenue Bond Debt > Revenue Bond Debt Amount Retired",
   "amounts": {
    "2016": 0,
    "2017": 0,
    "2018": 0,
    "2019": 0,
    "2020": 0,
    "2021": 0,
    "2022": 0,
    "2023": 137363
   }
  },
  {
   "classification": "Revenue Bond Debt Ending Amount Outstanding",
   "category": "debt",
   "section": "debt",
   "depth": 2,
   "path": "PART XI DEBT OUTSTANDING, ISSUED, RETIRED DURING FISCAL YEAR > Section A Revenue Bond Debt > Revenue Bond Debt Ending Amount Outstanding",
   "amounts": {
    "2016": 0,
    "2017": 0,
    "2018": 0,
    "2019": 0,
    "2020": 0,
    "2021": 0,
    "2022": 0,
    "2023": 4342927
   }
  },
  {
   "classification": "Revenue Bond Debt Interest Paid",
   "category": "debt",
   "section": "debt",
   "depth": 2,
   "path": "PART XI DEBT OUTSTANDING, ISSUED, RETIRED DURING FISCAL YEAR > Section A Revenue Bond Debt > Revenue Bond Debt Interest Paid",
   "amounts": {
    "2016": 0,
    "2017": 0,
    "2018": 0,
    "2019": 0,
    "2020": 0,
    "2021": 0,
    "2022": 0,
    "2023": 51990
   }
  },
  {
   "classification": "GO Bond Debt Beginning Amount Outstanding",
   "category": "debt",
   "section": "debt",
   "depth": 2,
   "path": "PART XI DEBT OUTSTANDING, ISSUED, RETIRED DURING FISCAL YEAR > Section B GO Bond Debt > GO Bond Debt Beginning Amount Outstanding",
   "amounts": {
    "2016": 0,
    "2017": 0,
    "2018": 0,
    "2019": 0,
    "2020": 0,
    "2021": 0,
    "2022": 0,
    "2023": 0
   }
  },
  {
   "classification": "GO Bond Debt New Issued Amount",
   "category": "debt",
   "section": "debt",
   "depth": 2,
   "path": "PART XI DEBT OUTSTANDING, ISSUED, RETIRED DURING FISCAL YEAR > Section B GO Bond Debt > GO Bond Debt New Issued Amount",
   "amounts": {
    "2016": 0,
    "2017": 0,
    "2018": 0,
    "2019": 0,
    "2020": 0,
    "2021": 0,
    "2022": 0,
    "2023": 0
   }
  },
  {
   "classification": "GO Bond Debt Amount Retired",
   "category": "debt",
   "section": "debt",
   "depth": 2,
   "path": "PART XI DEBT OUTSTANDING, ISSUED, RETIRED DURING FISCAL YEAR > Section B GO Bond Debt > GO Bond Debt Amount Retired",
   "amounts": {
    "2016": 0,
    "2017": 0,
    "2018": 0,
    "2019": 0,
    "2020": 0,
    "2021": 0,
    "2022": 0,
    "2023": 0
   }
  },
  {
   "classification": "GO Bond Debt Ending Amount Outstanding",
   "category": "debt",
   "section": "debt",
   "depth": 2,
   "path": "PART XI DEBT OUTSTANDING, ISSUED, RETIRED DURING FISCAL YEAR > Section B GO Bond Debt > GO Bond Debt Ending Amount Outstanding",
   "amounts": {
    "2016": 0,
    "2017": 0,
    "2018": 0,
    "2019": 0,
    "2020": 0,
    "2021": 0,
    "2022": 0,
    "2023": 0
   }
  },
  {
   "classification": "GO Bond Debt Interest Paid",
   "category": "debt",
   "section": "debt",
   "depth": 2,
   "path": "PART XI DEBT OUTSTANDING, ISSUED, RETIRED DURING FISCAL YEAR > Section B GO Bond Debt > GO Bond Debt Interest Paid",
   "amounts": {
    "2016": 0,
    "2017": 0,
    "2018": 0,
    "2019": 0,
    "2020": 0,
    "2021": 0,
    "2022": 0,
    "2023": 0
   }
  },
  {
   "classification": "Other Long-term Debt Beginning Amount Outstanding",
   "category": "debt",
   "section": "debt",
   "depth": 2,
   "path": "PART XI DEBT OUTSTANDING, ISSUED, RETIRED DURING FISCAL YEAR > Section C Other Long-term Debt > Other Long-term Debt Beginning Amount Outstanding",
   "amounts": {
    "2016": 78906,
    "2017": 386541,
    "2018": 575881,
    "2019": 679136,
    "2020": 2389238,
    "2021": 2835343,
    "2022": 4340999,
    "2023": 0
   }
  },
  {
   "classification": "Other Long-term Debt New Issued Amount",
   "category": "debt",
   "section": "debt",
   "depth": 2,
   "path": "PART XI DEBT OUTSTANDING, ISSUED, RETIRED DURING FISCAL YEAR > Section C Other Long-term Debt > Other Long-term Debt New Issued Amount",
   "amounts": {
    "2016": 386541,
    "2017": 200359,
    "2018": 125753,
    "2019": 1721585,
    "2020": 446105,
    "2021": 1508521,
    "2022": 151290,
    "2023": 0
   }
  },
  {
   "classification": "Other Long-term Debt Amount Retired",
   "category": "debt",
   "section": "debt",
   "depth": 2,
   "path": "PART XI DEBT OUTSTANDING, ISSUED, RETIRED DURING FISCAL YEAR > Section C Other Long-term Debt > Other Long-term Debt Amount Retired",
   "amounts": {
    "2016": 78906,
    "2017": 11019,
    "2018": 22498,
    "2019": 11483,
    "2020": 0,
    "2021": 2865,
    "2022": 11999,
    "2023": 0
   }
  },
  {
   "classification": "Other Long-term Debt Ending Amount Outstanding",
   "category": "debt",
   "section": "debt",
   "depth": 2,
   "path": "PART XI DEBT OUTSTANDING, ISSUED, RETIRED DURING FISCAL YEAR > Section C Other Long-term Debt > Other Long-term Debt Ending Amount Outstanding",
   "amounts": {
    "2016": 386541,
    "2017": 575881,
    "2018": 679136,
    "2019": 2389238,
    "2020": 2835343,
    "2021": 4340999,
    "2022": 4480290,
    "2023": 0
   }
  },
  {
   "classification": "Other Long-term Debt Interest Paid",
   "category": "debt",
   "section": "debt",
   "depth": 2,
   "path": "PART XI DEBT OUTSTANDING, ISSUED, RETIRED DURING FISCAL YEAR > Section C Other Long-term Debt > Other Long-term Debt Interest Paid",
   "amounts": {
    "2016": 3299,
    "2017": 556,
    "2018": 652,
    "2019": 92,
    "2020": 0,
    "2021": 2460,
    "2022": 51813,
    "2023": 0
   }
  },
  {
   "classification": "Capital Leases Payable Beginning Amount Outstanding",
   "category": "debt",
   "section": "debt",
   "depth": 2,
   "path": "PART XI DEBT OUTSTANDING, ISSUED, RETIRED DURING FISCAL YEAR > Section D Capital Leases Payable > Capital Leases Payable Beginning Amount Outstanding",
   "amounts": {
    "2016": 48917,
    "2017": 13503,
    "2018": 9228,
    "2019": 4731,
    "2020": 0,
    "2021": 0,
    "2022": 0,
    "2023": 0
   }
  },
  {
   "classification": "Capital Leases Payable New Issued Amount",
   "category": "debt",
   "section": "debt",
   "depth": 2,
   "path": "PART XI DEBT OUTSTANDING, ISSUED, RETIRED DURING FISCAL YEAR > Section D Capital Leases Payable > Capital Leases Payable New Issued Amount",
   "amounts": {
    "2016": 0,
    "2017": 0,
    "2018": 0,
    "2019": 0,
    "2020": 0,
    "2021": 0,
    "2022": 0,
    "2023": 0
   }
  },
  {
   "classification": "Capital Leases Payable Amount Retired",
   "category": "debt",
   "section": "debt",
   "depth": 2,
   "path": "PART XI DEBT OUTSTANDING, ISSUED, RETIRED DURING FISCAL YEAR > Section D Capital Leases Payable > Capital Leases Payable Amount Retired",
   "amounts": {
    "2016": 35414,
    "2017": 4275,
    "2018": 4497,
    "2019": 4731,
    "2020": 0,
    "2021": 0,
    "2022": 0,
    "2023": 0
   }
  },
  {
   "classification": "Capital Leases Payable Ending Amount Outstanding",
   "category": "debt",
   "section": "debt",
   "depth": 2,
   "path": "PART XI DEBT OUTSTANDING, ISSUED, RETIRED DURING FISCAL YEAR > Section D Capital Leases Payable > Capital Leases Payable Ending Amount Outstanding",
   "amounts": {
    "2016": 13503,
    "2017": 9228,
    "2018": 4731,
    "2019": 0,
    "2020": 0,
    "2021": 0,
    "2022": 0,
    "2023": 0
   }
  },
  {
   "classification": "Capital Leases Payable Interest Paid",
   "category": "debt",
   "section": "debt",
   "depth": 2,
   "path": "PART XI DEBT OUTSTANDING, ISSUED, RETIRED DURING FISCAL YEAR > Section D Capital Leases Payable > Capital Leases Payable Interest Paid",
   "amounts": {
    "2016": 1239,
    "2017": 700,
    "2018": 479,
    "2019": 245,
    "2020": 0,
    "2021": 0,
    "2022": 0,
    "2023": 0
   }
  },
  {
   "classification": "Short Term Notes Beginning Amount Outstanding",
   "category": "debt",
   "section": "debt",
   "depth": 2,
   "path": "PART XI DEBT OUTSTANDING, ISSUED, RETIRED DURING FISCAL YEAR > Section E Short Term Notes > Short Term Notes Beginning Amount Outstanding",
   "amounts": {
    "2016": 0,
    "2017": 0,
    "2018": 0,
    "2019": 0,
    "2020": 0,
    "2021": 0,
    "2022": 0,
    "2023": 0
   }
  },
  {
   "classification": "Short Term Notes New Issued Amount",
   "category": "debt",
   "section": "debt",
   "depth": 2,
   "path": "PART XI DEBT OUTSTANDING, ISSUED, RETIRED DURING FISCAL YEAR > Section E Short Term Notes > Short Term Notes New Issued Amount",
   "amounts": {
    "2016": 0,
    "2017": 0,
    "2018": 0,
    "2019": 0,
    "2020": 0,
    "2021": 0,
    "2022": 0,
    "2023": 0
   }
  },
  {
   "classification": "Short Term Notes Amount Retired",
   "category": "debt",
   "section": "debt",
   "depth": 2,
   "path": "PART XI DEBT OUTSTANDING, ISSUED, RETIRED DURING FISCAL YEAR > Section E Short Term Notes > Short Term Notes Amount Retired",
   "amounts": {
    "2016": 0,
    "2017": 0,
    "2018": 0,
    "2019": 0,
    "2020": 0,
    "2021": 0,
    "2022": 0,
    "2023": 0
   }
  },
  {
   "classification": "Short Term Notes Ending Amount Outstanding",
   "category": "debt",
   "section": "debt",
   "depth": 2,
   "path": "PART XI DEBT OUTSTANDING, ISSUED, RETIRED DURING FISCAL YEAR > Section E Short Term Notes > Short Term Notes Ending Amount Outstanding",
   "amounts": {
    "2016": 0,
    "2017": 0,
    "2018": 0,
    "2019": 0,
    "2020": 0,
    "2021": 0,
    "2022": 0,
    "2023": 0
   }
  },
  {
   "classification": "Short Term Notes Interest Paid",
   "category": "debt",
   "section": "debt",
   "depth": 2,
   "path": "PART XI DEBT OUTSTANDING, ISSUED, RETIRED DURING FISCAL YEAR > Section E Short Term Notes > Short Term Notes Interest Paid",
   "amounts": {
    "2016": 0,
    "2017": 0,
    "2018": 0,
    "2019": 0,
    "2020": 0,
    "2021": 0,
    "2022": 0,
    "2023": 0
   }
  },
  {
   "classification": "Special Assessment Debt Beginning Amount Outstanding",
   "category": "debt",
   "section": "debt",
   "depth": 2,
   "path": "PART XI DEBT OUTSTANDING, ISSUED, RETIRED DURING FISCAL YEAR > Section F Special Assessment Debt > Special Assessment Debt Beginning Amount Outstanding",
   "amounts": {
    "2016": 0,
    "2017": 0,
    "2018": 0,
    "2019": 0,
    "2020": 0,
    "2021": 0,
    "2022": 0,
    "2023": 0
   }
  },
  {
   "classification": "Special Assessment Debt New Issued Amount",
   "category": "debt",
   "section": "debt",
   "depth": 2,
   "path": "PART XI DEBT OUTSTANDING, ISSUED, RETIRED DURING FISCAL YEAR > Section F Special Assessment Debt > Special Assessment Debt New Issued Amount",
   "amounts": {
    "2016": 0,
    "2017": 0,
    "2018": 0,
    "2019": 0,
    "2020": 0,
    "2021": 0,
    "2022": 0,
    "2023": 0
   }
  },
  {
   "classification": "Special Assessment Debt Amount Retired",
   "category": "debt",
   "section": "debt",
   "depth": 2,
   "path": "PART XI DEBT OUTSTANDING, ISSUED, RETIRED DURING FISCAL YEAR > Section F Special Assessment Debt > Special Assessment Debt Amount Retired",
   "amounts": {
    "2016": 0,
    "2017": 0,
    "2018": 0,
    "2019": 0,
    "2020": 0,
    "2021": 0,
    "2022": 0,
    "2023": 0
   }
  },
  {
   "classification": "Special Assessment Debt Ending Amount Outstanding",
   "category": "debt",
   "section": "debt",
   "depth": 2,
   "path": "PART XI DEBT OUTSTANDING, ISSUED, RETIRED DURING FISCAL YEAR > Section F Special Assessment Debt > Special Assessment Debt Ending Amount Outstanding",
   "amounts": {
    "2016": 0,
    "2017": 0,
    "2018": 0,
    "2019": 0,
    "2020": 0,
    "2021": 0,
    "2022": 0,
    "2023": 0
   }
  },
  {
   "classification": "Special Assessment Debt Interest Paid",
   "category": "debt",
   "section": "debt",
   "depth": 2,
   "path": "PART XI DEBT OUTSTANDING, ISSUED, RETIRED DURING FISCAL YEAR > Section F Special Assessment Debt > Special Assessment Debt Interest Paid",
   "amounts": {
    "2016": 0,
    "2017": 0,
    "2018": 0,
    "2019": 0,
    "2020": 0,
    "2021": 0,
    "2022": 0,
    "2023": 0
   }
  },
  {
   "classification": "Fiscal Agent Fees for Year",
   "category": "debt",
   "section": "debt",
   "depth": 2,
   "path": "PART XI DEBT OUTSTANDING, ISSUED, RETIRED DURING FISCAL YEAR > Other Debt Costs > Fiscal Agent Fees for Year",
   "amounts": {
    "2016": 0,
    "2017": 0,
    "2018": 0,
    "2019": 0,
    "2020": 0,
    "2021": 0,
    "2022": 0,
    "2023": 0
   }
  },
  {
   "classification": "Issuance Costs",
   "category": "debt",
   "section": "debt",
   "depth": 2,
   "path": "PART XI DEBT OUTSTANDING, ISSUED, RETIRED DURING FISCAL YEAR > Other Debt Costs > Issuance Costs",
   "amounts": {
    "2016": 0,
    "2017": 0,
    "2018": 0,
    "2019": 0,
    "2020": 0,
    "2021": 0,
    "2022": 0,
    "2023": 0
   }
  },
  {
   "classification": "Advanced Refunding Esc.",
   "category": "debt",
   "section": "debt",
   "depth": 2,
   "path": "PART XI DEBT OUTSTANDING, ISSUED, RETIRED DURING FISCAL YEAR > Other Debt Costs > Advanced Refunding Esc.",
   "amounts": {
    "2016": 0,
    "2017": 0,
    "2018": 0,
    "2019": 0,
    "2020": 0,
    "2021": 0,
    "2022": 0,
    "2023": 0
   }
  }
 ]
}
